{
  "status": "completed",
  "created_at": "2026-07-12T20:41:11.635077+00:00",
  "started_at": "2026-07-12T20:41:11.699793+00:00",
  "finished_at": "2026-07-12T20:53:13.549901+00:00",
  "best": {
    "epoch": 4,
    "val_acc": 0.9505,
    "val_loss": 0.61576,
    "val_per_step_acc": [
      0.26367,
      0.55983,
      0.69267,
      0.7665,
      0.80817,
      0.84533,
      0.87567,
      0.9035,
      0.92033,
      0.9345,
      0.94733,
      0.9505
    ]
  },
  "final_test": {
    "loss": 0.5974,
    "acc": 0.9488,
    "per_step_acc": [
      0.2932,
      0.5564,
      0.6983,
      0.776,
      0.815,
      0.8446,
      0.8807,
      0.9063,
      0.9227,
      0.9375,
      0.9466,
      0.9488
    ]
  },
  "error": null
}